chronometry/__init__.py
chronometry/date/YearMonth.py
chronometry/date/YearQuarter.py
chronometry/date/__init__.py
chronometry/date/add_time.py
chronometry/date/convert_string_to_date.py
chronometry/date/get_date_part.py
chronometry/date/get_first_day_of_month.py
chronometry/date/get_month.py
chronometry/date/get_number_of_days.py
chronometry/date/get_quarter.py
chronometry/date/get_today.py
chronometry/date/parse_date.py
chronometry/date/remove_non_alphanumeric.py
chronometry/estimate/Estimator.py
chronometry/estimate/Measurement.py
chronometry/estimate/__init__.py
chronometry/estimate/create_arguments.py
chronometry/numbers/FlexibleNumber.py
chronometry/numbers/NumberPart.py
chronometry/numbers/__init__.py
chronometry/progress/Iterable.py
chronometry/progress/ProgressBar.py
chronometry/progress/__init__.py
chronometry/progress/colour.py
chronometry/progress/map.py
chronometry/time/MeasurementSet.py
chronometry/time/TimeMeasurement.py
chronometry/time/Timer.py
chronometry/time/__init__.py
chronometry/time/convert.py
chronometry/time/get_elapsed.py
chronometry/time/get_time.py
chronometry/time/measure.py
chronometry-2020.11.12.dist-info/LICENSE
chronometry-2020.11.12.dist-info/METADATA
chronometry-2020.11.12.dist-info/WHEEL
chronometry-2020.11.12.dist-info/top_level.txt
chronometry-2020.11.12.dist-info/RECORD
