Metadata-Version: 2.1
Name: chronometry
Version: 2020.11.12
Summary: Python library for tracking time and displaying progress bars
Home-page: https://github.com/idin/chronometry
Author: Idin
Author-email: py@idin.ca
License: MIT
Platform: UNKNOWN
Requires-Python: ~=3.6
